[{"Tipo":"Autobot","Nombre":"Bumblebee","Apodo":"\u0022El soldado m\u00E1s valiente\u0022","FechaNacimiento":"1752-12-09T00:00:00","ModoAlterno":"Chevrolet Camaro SS","Edad":271,"Velocidad":3,"Destreza":1,"Fuerza":6,"Nivel":3,"Armadura":7,"Salud":100},{"Tipo":"Autobot","Nombre":"Ironhide","Apodo":"\u0022El protector veterano\u0022","FechaNacimiento":"1879-06-14T00:00:00","ModoAlterno":"Hummer H2","Edad":144,"Velocidad":8,"Destreza":2,"Fuerza":9,"Nivel":8,"Armadura":9,"Salud":100},{"Tipo":"Decepticon","Nombre":"Blitzwing","Apodo":"\u0022El trueno temible\u0022","FechaNacimiento":"1944-02-07T00:00:00","ModoAlterno":"McDonnell Douglas F/A-18 Hornet","Edad":79,"Velocidad":10,"Destreza":2,"Fuerza":3,"Nivel":10,"Armadura":6,"Salud":100},{"Tipo":"Decepticon","Nombre":"Ravage","Apodo":"\u0022El depredador sigiloso\u0022","FechaNacimiento":"1910-04-27T00:00:00","ModoAlterno":"Condor II UAV","Edad":113,"Velocidad":9,"Destreza":2,"Fuerza":1,"Nivel":8,"Armadura":10,"Salud":100}]